easypaint/__init__.py
easypaint/easypaint.py
easypaint/libsimple3d.py
easypaint/demos/__init__.py
easypaint/demos/demo00_size.py
easypaint/demos/demo01_primitives.py
easypaint/demos/demo02_gravity.py
easypaint/demos/demo03_3d.py
easypaint/demos/demo04_moving.py
easypaint/demos/demo05_circles.py
easypaint/demos/demo06_spyro.py
easypaint/demos/demo07_mouse_drawing.py
easypaint/demos/demo08_mouse_clicking.py
easypaint/demos/demo09_readkey.py
easypaint/demos/demo10_soma_anim.py
easypaint-1.0.7.dist-info/LICENSE
easypaint-1.0.7.dist-info/METADATA
easypaint-1.0.7.dist-info/WHEEL
easypaint-1.0.7.dist-info/top_level.txt
easypaint-1.0.7.dist-info/RECORD
