Metadata-Version: 2.1
Name: easypaint
Version: 1.0.7
Summary: Biblioteca de dibujo para Python 3 (requiere python-tk)
Author-email: David LLorens <dllorens@uji.es>
License: GNU Affero General Public License v3
Project-URL: Homepage, https://github.com/DavidLlorens/easypaint
Keywords: algoritmia,canvas,pythong,easycanvas
Classifier: Programming Language :: Python :: 3
Classifier: Operating System :: OS Independent
Requires-Python: >=3.8
License-File: LICENSE
